dupegrouper/__init__.py
dupegrouper/base.py
dupegrouper/definitions.py
dupegrouper/strategies/__init__.py
dupegrouper/strategies/custom.py
dupegrouper/strategies/exact.py
dupegrouper/strategies/fuzzy.py
dupegrouper/strategies/tfidf.py
dupegrouper/strategy.py
dupegrouper/wrappers/__init__.py
dupegrouper/wrappers/dataframe.py
dupegrouper/wrappers/dataframes/__init__.py
dupegrouper/wrappers/dataframes/_pandas.py
dupegrouper/wrappers/dataframes/_polars.py
dupegrouper/wrappers/dataframes/_spark.py
dupegrouper-0.2.0.dist-info/LICENSE
dupegrouper-0.2.0.dist-info/METADATA
dupegrouper-0.2.0.dist-info/NOTICE
dupegrouper-0.2.0.dist-info/WHEEL
dupegrouper-0.2.0.dist-info/RECORD
