Metadata-Version: 2.3
Name: dupegrouper
Version: 0.2.0
Summary: A Python library for grouping duplicate data efficiently.
License: Apache-2.0
Keywords: duplicates,deduplication,grouping
Author: VictorAutonell-Oiry
Requires-Python: >=3.9,<4.0
Classifier: Development Status :: 2 - Pre-Alpha
Classifier: Intended Audience :: Developers
Classifier: Intended Audience :: Science/Research
Classifier: License :: OSI Approved :: Apache Software License
Classifier: Programming Language :: Python :: 3
Classifier: Programming Language :: Python :: 3.9
Classifier: Programming Language :: Python :: 3.10
Classifier: Programming Language :: Python :: 3.11
Classifier: Programming Language :: Python :: 3.12
Classifier: Programming Language :: Python :: 3.13
Classifier: Topic :: Software Development :: Libraries :: Python Modules
Requires-Dist: multipledispatch (>=1.0.0,<2.0.0)
Requires-Dist: pandas (>=2.2.3,<3.0.0)
Requires-Dist: polars (>=1.24.0,<2.0.0)
Requires-Dist: pyspark (>=3.5.5,<4.0.0)
Requires-Dist: rapidfuzz (>=3.12.2,<4.0.0)
Requires-Dist: scikit-learn (>=1.6.1,<2.0.0)
Requires-Dist: sparse-dot-topn (>=1.1.5,<2.0.0)
Requires-Dist: typing-extensions (>=4.13.0,<5.0.0)
Project-URL: Documentation, https://victorautonell-oiry.me/dupegrouper/dupegrouper.html
Project-URL: Repository, https://github.com/VictorAut/dupegrouper/
